kytos/__init__.py
kytos/core/__init__.py
kytos/core/api_server.py
kytos/core/atcp_server.py
kytos/core/auth.py
kytos/core/buffers.py
kytos/core/common.py
kytos/core/config.py
kytos/core/connection.py
kytos/core/constants.py
kytos/core/controller.py
kytos/core/events.py
kytos/core/exceptions.py
kytos/core/helpers.py
kytos/core/interface.py
kytos/core/kytosd.py
kytos/core/link.py
kytos/core/logs.py
kytos/core/metadata.py
kytos/core/switch.py
kytos/core/websocket.py
kytos/core/napps/__init__.py
kytos/core/napps/base.py
kytos/core/napps/manager.py
kytos/core/napps/napp_dir_listener.py
kytos/lib/__init__.py
kytos/lib/helpers.py
kytos/templates/kytos.conf.template
kytos/templates/logging.ini.template
kytos-2021.1.data/scripts/kytosd
tests/unit/__init__.py
tests/unit/test_core/__init__.py
tests/unit/test_core/test_api_server.py
tests/unit/test_core/test_atcp_server.py
tests/unit/test_core/test_auth.py
tests/unit/test_core/test_buffers.py
tests/unit/test_core/test_common.py
tests/unit/test_core/test_connection.py
tests/unit/test_core/test_controller.py
tests/unit/test_core/test_events.py
tests/unit/test_core/test_exceptions.py
tests/unit/test_core/test_helpers.py
tests/unit/test_core/test_interface.py
tests/unit/test_core/test_kytosd.py
tests/unit/test_core/test_link.py
tests/unit/test_core/test_logs.py
tests/unit/test_core/test_napp_dir_listener.py
tests/unit/test_core/test_napps_base.py
tests/unit/test_core/test_napps_manager.py
tests/unit/test_core/test_switch.py
tests/unit/test_core/test_websocket.py
tests/unit/test_lib/__init__.py
tests/unit/test_lib/test_helpers.py
kytos-2021.1.dist-info/AUTHORS.rst
kytos-2021.1.dist-info/LICENSE
kytos-2021.1.dist-info/METADATA
kytos-2021.1.dist-info/WHEEL
kytos-2021.1.dist-info/top_level.txt
kytos-2021.1.dist-info/RECORD
