Metadata-Version: 2.1
Name: kytos
Version: 2021.1
Summary: Kytos, an open source SDN Platform
Home-page: https://github.com/kytos/kytos
Author: Kytos Team
License: MIT
Platform: UNKNOWN
Classifier: License :: OSI Approved :: MIT License
Classifier: Operating System :: POSIX :: Linux
Classifier: Programming Language :: Python :: 3.6
Classifier: Topic :: System :: Networking
Classifier: Development Status :: 4 - Beta
Classifier: Environment :: Console
Classifier: Environment :: No Input/Output (Daemon)
Requires-Dist: backcall (==0.1.0)
Requires-Dist: click (==7.1.1)
Requires-Dist: decorator (==4.4.2)
Requires-Dist: docutils (>=0.16)
Requires-Dist: flask-cors (==3.0.8)
Requires-Dist: flask-socketio (==4.2.1)
Requires-Dist: flask (==1.1.2)
Requires-Dist: ipython-genutils (==0.2.0)
Requires-Dist: ipython (==7.13.0)
Requires-Dist: itsdangerous (==1.1.0)
Requires-Dist: janus (==0.4.0)
Requires-Dist: jedi (==0.16.0)
Requires-Dist: jinja2 (==2.11.1)
Requires-Dist: lockfile (==0.12.2)
Requires-Dist: markupsafe (==1.1.1)
Requires-Dist: parso (==0.6.2)
Requires-Dist: pathtools (==0.1.2)
Requires-Dist: pexpect (==4.8.0)
Requires-Dist: pickleshare (==0.7.5)
Requires-Dist: prompt-toolkit (==3.0.5)
Requires-Dist: ptyprocess (==0.6.0)
Requires-Dist: pygments (>=2.8.1)
Requires-Dist: pyjwt (==1.7.1)
Requires-Dist: python-daemon (==2.2.4)
Requires-Dist: python-engineio (==3.12.1)
Requires-Dist: python-openflow (==2021.1)
Requires-Dist: python-socketio (==4.5.1)
Requires-Dist: six (>=1.15.0)
Requires-Dist: traitlets (==4.3.3)
Requires-Dist: watchdog (==0.10.2)
Requires-Dist: wcwidth (==0.1.9)
Requires-Dist: werkzeug (==1.0.1)
